topsis/__init__.py
topsis/topsis.py
Topsis_Sahil_102067006-1.0.0.dist-info/LICENSE.txt
Topsis_Sahil_102067006-1.0.0.dist-info/METADATA
Topsis_Sahil_102067006-1.0.0.dist-info/WHEEL
Topsis_Sahil_102067006-1.0.0.dist-info/entry_points.txt
Topsis_Sahil_102067006-1.0.0.dist-info/top_level.txt
Topsis_Sahil_102067006-1.0.0.dist-info/RECORD
