Metadata-Version: 2.1
Name: Topsis-Sahil-102067006
Version: 1.0.0
Summary: topsis package for MCDM problems
Home-page: https://github.com/sahil1239
Author: Sahil Singla
Author-email: ssingla_be20@thapar.edu
Classifier: Programming Language :: Python :: 3.7
Classifier: Programming Language :: Python :: 3.8
Classifier: License :: OSI Approved :: MIT License
License-File: LICENSE.txt
